bazel_mcp/__init__.py
bazel_mcp/bazel.py
bazel_mcp/server.py
bazel_mcp/targets.py
bazel_mcp/util.py
bazel_mcp-1.0.2.dist-info/licenses/LICENSE
bazel_mcp-1.0.2.dist-info/METADATA
bazel_mcp-1.0.2.dist-info/WHEEL
bazel_mcp-1.0.2.dist-info/entry_points.txt
bazel_mcp-1.0.2.dist-info/top_level.txt
bazel_mcp-1.0.2.dist-info/RECORD
