Metadata-Version: 2.4
Name: bazel-mcp
Version: 1.0.2
Summary: MCP server exposing Bazel build/run/test/query as tools
Author: Sandeep Menon
License: MIT
Requires-Python: >=3.10
License-File: LICENSE
Requires-Dist: mcp>=1.2.0
Dynamic: license-file
